move_ugc/__init__.py
move_ugc/gql_requests/__init__.py
move_ugc/gql_requests/additional_file.py
move_ugc/gql_requests/camera_settings.py
move_ugc/gql_requests/client.py
move_ugc/gql_requests/file.py
move_ugc/gql_requests/fragments.py
move_ugc/gql_requests/inputs.py
move_ugc/gql_requests/job.py
move_ugc/gql_requests/rig.py
move_ugc/gql_requests/take.py
move_ugc/gql_requests/volume.py
move_ugc/gql_requests/webhook_endpoint.py
move_ugc/py.typed
move_ugc/schemas/__init__.py
move_ugc/schemas/client.py
move_ugc/schemas/commons.py
move_ugc/schemas/constants.py
move_ugc/schemas/file.py
move_ugc/schemas/gql.py
move_ugc/schemas/inputs.py
move_ugc/schemas/job.py
move_ugc/schemas/metaclient.py
move_ugc/schemas/progress.py
move_ugc/schemas/rig.py
move_ugc/schemas/sources.py
move_ugc/schemas/sync_method.py
move_ugc/schemas/take.py
move_ugc/schemas/transport.py
move_ugc/schemas/volume.py
move_ugc/schemas/webhook_endpoint.py
move_ugc/services/__init__.py
move_ugc/services/base.py
move_ugc/services/camera_settings.py
move_ugc/services/client.py
move_ugc/services/file.py
move_ugc/services/job.py
move_ugc/services/rig.py
move_ugc/services/take.py
move_ugc/services/volume.py
move_ugc/services/webhooks.py
move_ugc/settings.py
move_ugc/ugc_client.py
move_ugc_python-4.1.0.dist-info/METADATA
move_ugc_python-4.1.0.dist-info/WHEEL
move_ugc_python-4.1.0.dist-info/RECORD
