Metadata-Version: 2.1
Name: move-ugc-python
Version: 4.1.0
Summary: 
Author: Move.ai
Requires-Python: >=3.9.1,<4.0.0
Classifier: Programming Language :: Python :: 3
Classifier: Programming Language :: Python :: 3.10
Classifier: Programming Language :: Python :: 3.11
Classifier: Programming Language :: Python :: 3.12
Classifier: Programming Language :: Python :: 3.13
Requires-Dist: gql[requests] (>=3.4.1,<4.0.0)
Requires-Dist: pydantic (>=2.10.6,<3.0.0)
Requires-Dist: pydantic-settings (>=2.8.1,<3.0.0)
